jupytergis/tiler/__init__.py
jupytergis/tiler/gis_document.py
jupytergis/tiler/handler.py
jupytergis/tiler/server_extension.py
jupytergis_tiler-0.2.1.data/data/etc/jupyter/jupyter_server_config.d/jupytergis_tiler.json
jupytergis_tiler-0.2.1.dist-info/METADATA
jupytergis_tiler-0.2.1.dist-info/WHEEL
jupytergis_tiler-0.2.1.dist-info/licenses/LICENSE
jupytergis_tiler-0.2.1.dist-info/RECORD
