Metadata-Version: 2.4
Name: jupytergis-tiler
Version: 0.2.1
Summary: Tiler layer for JupyterGIS
Author-email: David Brochart <david.brochart@gmail.com>
License: MIT License
License-File: LICENSE
Keywords: gis,jupyter
Classifier: Development Status :: 4 - Beta
Classifier: Intended Audience :: Developers
Classifier: License :: OSI Approved :: MIT License
Classifier: Programming Language :: Python
Classifier: Programming Language :: Python :: 3.10
Classifier: Programming Language :: Python :: 3.11
Classifier: Programming Language :: Python :: 3.12
Classifier: Programming Language :: Python :: 3.13
Classifier: Programming Language :: Python :: 3.14
Requires-Python: <3.14,>=3.10
Requires-Dist: anycorn
Requires-Dist: anyio
Requires-Dist: fastapi
Requires-Dist: httpx
Requires-Dist: jupyter-server
Requires-Dist: jupytergis<0.12,>=0.11
Requires-Dist: rio-tiler>=7.7.1
Requires-Dist: titiler
Requires-Dist: tornado
Requires-Dist: xarray
